dags/__init__.py
dags/airflow_dag.py
dags/anonymize_dag.py
dags/anonymize_query_dag.py
dags/archive_dag.py
dags/audience_analysis_dag.py
dags/barnacle_dag.py
dags/barnacle_dv360_dag.py
dags/bigquery_census_correlate_dag.py
dags/bigquery_census_normalize_dag.py
dags/bigquery_function_dag.py
dags/bigquery_pearson_significance_dag.py
dags/bigquery_pearson_significance_test_dag.py
dags/bigquery_query_dag.py
dags/bigquery_run_query_dag.py
dags/bigquery_storage_dag.py
dags/bigquery_to_sheet_dag.py
dags/bigquery_view_dag.py
dags/bucket_dag.py
dags/bulk_dv360_dag.py
dags/bulkdozer_dag.py
dags/cm360_campaign_comparison_dag.py
dags/cm360_conversion_upload_from_bigquery_dag.py
dags/cm360_conversion_upload_from_sheets_dag.py
dags/cm360_data_warehouse_dag.py
dags/cm360_oculi_dag.py
dags/cm360_report_replicate_dag.py
dags/cm360_segmentology_dag.py
dags/cm360_to_dv360_dag.py
dags/cm_campaign_audit_dag.py
dags/cm_to_dv360_io_dag.py
dags/cm_user_editor_dag.py
dags/conversion_upload_from_biguery_dag.py
dags/conversion_upload_from_sheets_dag.py
dags/ctv_audience_affinity_dag.py
dags/dataset_dag.py
dags/dbm_dag.py
dags/dbm_to_bigquery_dag.py
dags/dbm_to_sheets_dag.py
dags/dbm_to_storage_dag.py
dags/dcm_api_to_bigquery_dag.py
dags/dcm_bulk_standard_dag.py
dags/dcm_dag.py
dags/dcm_log_dag.py
dags/dcm_replicate_to_bigquery_dag.py
dags/dcm_run_dag.py
dags/dcm_to_bigquery_dag.py
dags/dcm_to_sheets_dag.py
dags/dcm_to_storage_dag.py
dags/deal_finder_dag.py
dags/drive_copy_dag.py
dags/dt_dag.py
dags/dv360_api_insert_from_bigquery_dag.py
dags/dv360_api_patch_from_bigquery_dag.py
dags/dv360_api_to_bigquery_dag.py
dags/dv360_data_warehouse_dag.py
dags/dv360_editor_dag.py
dags/dv360_feature_adoption_dag.py
dags/dv360_segmentology_dag.py
dags/dv360_targeter_dag.py
dags/dv360_targeting_audit_dag.py
dags/dynamic_costs_dag.py
dags/email_cm_to_bigquery_dag.py
dags/email_dv360_to_bigquery_dag.py
dags/email_to_bigquery_dag.py
dags/floodlight_monitor_dag.py
dags/fred_regional_to_bigquery_dag.py
starthinker-2.1.6.dist-info/AUTHORS
starthinker-2.1.6.dist-info/LICENSE
starthinker-2.1.6.dist-info/METADATA
starthinker-2.1.6.dist-info/WHEEL
starthinker-2.1.6.dist-info/entry_points.txt
starthinker-2.1.6.dist-info/top_level.txt
starthinker-2.1.6.dist-info/RECORD
