Metadata-Version: 2.1
Name: starthinker
Version: 2.1.6
Summary: StarThinker is a Google gTech built python framework for creating and sharing re-usable workflow components.
Home-page: https://github.com/google/starthinker
Author: Paul Kenjora
Author-email: kenjora@google.com
License: Apache License, Version 2.0
Keywords: starthinker
Platform: UNKNOWN
Classifier: Development Status :: 4 - Beta
Classifier: Intended Audience :: Developers
Classifier: License :: OSI Approved :: Apache Software License
Classifier: Natural Language :: English
Classifier: Programming Language :: Python :: 3
License-File: LICENSE
License-File: AUTHORS
Requires-Dist: google-api-python-client
Requires-Dist: google-auth
Requires-Dist: google-auth-oauthlib
Requires-Dist: google-auth-httplib2
Requires-Dist: google-cloud-bigquery (==2.34.1)
Requires-Dist: pysftp
Requires-Dist: pytz
Requires-Dist: tzlocal
Requires-Dist: TwitterAPI
Requires-Dist: python-dateutil
Requires-Dist: psutil
Requires-Dist: moviepy (==1.0.0)
Requires-Dist: py-xlsx
Requires-Dist: simple-salesforce
Requires-Dist: smartsheet-python-sdk
